{
  "default": {
    "groups": {
      "nil": {
        "perms": []
      },
      "users": {
        "parent": "",
        "perms": [
          "инфа",
          "кто",
          "выбери",
          "бебра",
          "правда",
          "вера"
        ]
      },
      "friends": {
        "parent": "users",
        "perms": [
          "напиши",
          "следуй",
          "кальмар",
          "опрос"
        ]
      },
      "op": {
        "parent": "friends",
        "perms": [
          "контроль",
          "выйди"
        ]
      }
    },
    "users": {
      "default": {
        "group": "users",
        "perms": []
      },
      "CinemaFoxProd": {
        "group": "op",
        "perms": []
      },
      "Console": {
        "group": "op",
        "perms": []
      }
    }
  }
}